upload_files_to_github.py
upload_files_to_github-1.3.dist-info/METADATA
upload_files_to_github-1.3.dist-info/WHEEL
upload_files_to_github-1.3.dist-info/entry_points.txt
upload_files_to_github-1.3.dist-info/top_level.txt
upload_files_to_github-1.3.dist-info/RECORD
