Metadata-Version: 2.1
Name: upload-files-to-github
Version: 1.3
Summary: UNKNOWN
License: UNKNOWN
Platform: UNKNOWN
Requires-Dist: argparse
Requires-Dist: requests
Requires-Dist: python-dotenv
